nldb/__init__.py
nldb/api.py
nldb/cli.py
nldb/config.py
nldb/core.py
nldb/templates/Dockerfile
nldb/templates/index.html
nldb/templates/prompt.txt
nldb-0.4.0.dist-info/entry_points.txt
nldb-0.4.0.dist-info/LICENSE
nldb-0.4.0.dist-info/WHEEL
nldb-0.4.0.dist-info/METADATA
nldb-0.4.0.dist-info/RECORD
