Metadata-Version: 2.1
Name: nldb
Version: 0.4.0
Summary: talk to your database
Author-email: Tom Dyson <tom@torchbox.com>
Classifier: License :: OSI Approved :: MIT License
Requires-Dist: openai
Requires-Dist: fastapi
Requires-Dist: uvicorn[standard]
Requires-Dist: tabulate
Requires-Dist: typer
Requires-Dist: duckdb
Requires-Dist: matplotlib
Requires-Dist: python-dotenv
Project-URL: Home, https://github.com/tomdyson/nldb
